sekai_libs/__init__.py
sekai_libs/math/array.cairo
sekai_libs/string/constants.cairo
sekai_libs/string/manipulation.cairo
sekai_libs/string/store.cairo
sekai_starknet_libraries-0.0.1.dist-info/LICENSE
sekai_starknet_libraries-0.0.1.dist-info/METADATA
sekai_starknet_libraries-0.0.1.dist-info/WHEEL
sekai_starknet_libraries-0.0.1.dist-info/top_level.txt
sekai_starknet_libraries-0.0.1.dist-info/RECORD
