Metadata-Version: 2.1
Name: sekai-starknet-libraries
Version: 0.0.1
Summary: Cairo Libraries for use in StarkNet
Home-page: https://github.com/sekai-studio/starknet-libs
Author: Sekai
Author-email: maintainers@sekai.gg
License: MIT
Platform: any
Classifier: Operating System :: OS Independent
License-File: LICENSE
Requires-Dist: importlib-metadata (>=4.0)
Provides-Extra: testing
Requires-Dist: setuptools ; extra == 'testing'
Requires-Dist: build ; extra == 'testing'
Requires-Dist: pytest ; extra == 'testing'
